CHANGES.rst
LICENCE
MANIFEST.in
README.rst
setup.py
docs/source/changes.rst
docs/source/conf.py
docs/source/development.rst
docs/source/index.rst
docs/source/overview.rst
docs/source/rays.rst
rays.egg-info/PKG-INFO
rays.egg-info/SOURCES.txt
rays.egg-info/dependency_links.txt
rays.egg-info/entry_points.txt
rays.egg-info/not-zip-safe
rays.egg-info/top_level.txt
src/rays/__init__.py
src/rays/compat.py
src/samples/asynchronous/asynchronous.py
src/samples/blog/gunicorn_conf.py
src/samples/blog/index.py
src/samples/blog/statics/base.css
src/samples/blog/templates/_admin_menu.html
src/samples/blog/templates/_entry.html
src/samples/blog/templates/admin_entry_new.html
src/samples/blog/templates/admin_index.html
src/samples/blog/templates/admin_signin_form.html
src/samples/blog/templates/layout.html
src/samples/blog/templates/show_entries.html
src/samples/blog/templates/show_entry.html
src/samples/blog/templates/caches/__keepme__
src/samples/websocketchat/index.py
src/samples/websocketchat/statics/base.css
src/samples/websocketchat/templates/index.html
src/samples/websocketchat/templates/layout.html
src/samples/websocketchat/templates/caches/__keepme__