Metadata-Version: 1.1
Name: rays
Version: 0.4.3
Summary: A "LESS PAIN" lightweight WSGI compatible web framework
Home-page: https://github.com/yuin/rays
Author: Yusuke Inuzuka
Author-email: yuin@inforno.net
License: MIT
Keywords: WSGI,web,framework,cgi
Platform: Platform Independent
Classifier: Programming Language :: Python :: 2.6
Classifier: Programming Language :: Python :: 2.7
Classifier: Programming Language :: Python :: 3.2
Classifier: Programming Language :: Python :: 3.3
Classifier: Development Status :: 4 - Beta
Classifier: License :: OSI Approved :: MIT License
Classifier: Operating System :: OS Independent
Classifier: Intended Audience :: Developers
Classifier: Topic :: Software Development :: Libraries :: Application Frameworks
Classifier: Topic :: Internet :: WWW/HTTP :: Dynamic Content :: CGI Tools/Libraries
